{"SLAM": {"2201.12726": "|**2022-01-30**|**Joint Vehicular Localization and Reflective Mapping Based on Team Channel-SLAM**|Xinghe Chu, Zhaoming Lu, David Gesbert, Luhan Wang, Xiangming Wen, Muqing Wu, Meiling Li|[2201.12726v1](http://arxiv.org/abs/2201.12726v1)|null|\n", "2201.12047": "|**2022-01-28**|**RGB-D SLAM Using Attention Guided Frame Association**|Ali Caglayan, Nevrez Imamoglu, Oguzhan Guclu, Ali Osman Serhatoglu, Weimin Wang, Ahmet Burak Can, Ryosuke Nakamura|[2201.12047v1](http://arxiv.org/abs/2201.12047v1)|null|\n", "2201.09862": "|**2022-01-24**|**Learning to Act with Affordance-Aware Multimodal Neural SLAM**|Zhiwei Jia, Kaixiang Lin, Yizhou Zhao, Qiaozi Gao, Govind Thattai, Gaurav Sukhatme|[2201.09862v1](http://arxiv.org/abs/2201.09862v1)|**[link](https://github.com/amazon-research/multimodal-neuralslam)**|\n", "2201.09048": "|**2022-01-22**|**Phase-SLAM: Phase Based Simultaneous Localization and Mapping for Mobile Structured Light Illumination Systems**|Xi Zheng, Rui Ma, Rui Gao, Qi Hao|[2201.09048v1](http://arxiv.org/abs/2201.09048v1)|**[link](https://github.com/zhengxi-git/phase-slam)**|\n", "2201.06423": "|**2022-01-17**|**SC-LiDAR-SLAM: a Front-end Agnostic Versatile LiDAR SLAM System**|Giseop Kim, Seungsang Yun, Jeongyun Kim, Ayoung Kim|[2201.06423v1](http://arxiv.org/abs/2201.06423v1)|null|\n", "2201.05386": "|**2022-01-14**|**SRVIO: Super Robust Visual Inertial Odometry for dynamic environments and challenging Loop-closure conditions**|Ali Samadzadeh, Ahmad Nickabadi|[2201.05386v1](http://arxiv.org/abs/2201.05386v1)|**[link](https://github.com/aa-samad/srvio)**|\n", "2201.03814": "|**2022-01-11**|**Multi-Hypothesis Scan Matching through Clustering**|Giorgio Iavicoli, Claudio Zito|[2201.03814v2](http://arxiv.org/abs/2201.03814v2)|null|\n", "2201.03773": "|**2022-01-11**|**Performance Guarantees for Spectral Initialization in Rotation Averaging and Pose-Graph SLAM**|Kevin J. Doherty, David M. Rosen, John J. Leonard|[2201.03773v1](http://arxiv.org/abs/2201.03773v1)|null|\n", "2201.03364": "|**2022-01-10**|**High-resolution Ecosystem Mapping in Repetitive Environments Using Dual Camera SLAM**|Brian M. Hopkinson, Suchendra M. Bhandarkar|[2201.03364v1](http://arxiv.org/abs/2201.03364v1)|**[link](https://github.com/bmhopkinson/hyslam)**|\n", "2201.03212": "|**2022-01-10**|**Why-So-Deep: Towards Boosting Previously Trained Models for Visual Place Recognition**|M. Usman Maqbool Bhutta, Yuxiang Sun, Darwin Lau, Ming Liu|[2201.03212v1](http://arxiv.org/abs/2201.03212v1)|null|\n"}, "Camera Localization": {"2201.05816": "|**2022-01-15**|**A Critical Analysis of Image-based Camera Pose Estimation Techniques**|Meng Xu, Youchen Wang, Bin Xu, Jun Zhang, Jian Ren, Stefan Poslad, Pengfei Xu|[2201.05816v1](http://arxiv.org/abs/2201.05816v1)|null|\n", "2112.12785": "|**2021-12-23**|**NinjaDesc: Content-Concealing Visual Descriptors via Adversarial Learning**|Tony Ng, Hyo Jin Kim, Vincent Lee, Daniel Detone, Tsun-Yi Yang, Tianwei Shen, Eddy Ilg, Vassileios Balntas, Krystian Mikolajczyk, Chris Sweeney|[2112.12785v1](http://arxiv.org/abs/2112.12785v1)|null|\n", "2112.02469": "|**2021-12-05**|**RADA: Robust Adversarial Data Augmentation for Camera Localization in Challenging Weather**|Jialu Wang, Muhamad Risqi U. Saputra, Chris Xiaoxuan Lu, Niki Trigon, Andrew Markham|[2112.02469v1](http://arxiv.org/abs/2112.02469v1)|null|\n", "2109.09884": "|**2021-09-20**|**Efficient shape mapping through dense touch and vision**|Sudharshan Suresh, Zilin Si, Joshua G. Mangelson, Wenzhen Yuan, Michael Kaess|[2109.09884v1](http://arxiv.org/abs/2109.09884v1)|null|\n", "2109.07339": "|**2021-09-15**|**S3LAM: Structured Scene SLAM**|Mathieu Gonzalez, Eric Marchand, Amine Kacete, J\u00e9r\u00f4me Royan|[2109.07339v1](http://arxiv.org/abs/2109.07339v1)|null|\n", "2109.06296": "|**2021-09-13**|**Monocular Camera Localization for Automated Vehicles Using Image Retrieval**|Eunhyek Joa, Francesco Borrelli|[2109.06296v1](http://arxiv.org/abs/2109.06296v1)|null|\n", "2108.09112": "|**2021-08-20**|**Continual Learning for Image-Based Camera Localization**|Shuzhe Wang, Zakaria Laskar, Iaroslav Melekhov, Xiaotian Li, Juho Kannala|[2108.09112v1](http://arxiv.org/abs/2108.09112v1)|**[link](https://github.com/aaltovision/cl_hscnet)**|\n", "2108.03819": "|**2021-08-09**|**DistillPose: Lightweight Camera Localization Using Auxiliary Learning**|Yehya Abouelnaga, Mai Bui, Slobodan Ilic|[2108.03819v1](http://arxiv.org/abs/2108.03819v1)|null|\n", "2107.03890": "|**2021-07-08**|**Uncertainty-Aware Camera Pose Estimation from Points and Lines**|Alexander Vakhitov, Luis Ferraz Colomina, Antonio Agudo, Francesc Moreno-Noguer|[2107.03890v1](http://arxiv.org/abs/2107.03890v1)|null|\n", "2107.03068": "|**2021-07-07**|**Video-Based Camera Localization Using Anchor View Detection and Recursive 3D Reconstruction**|Hajime Taira, Koki Onbe, Naoyuki Miyashita, Masatoshi Okutomi|[2107.03068v1](http://arxiv.org/abs/2107.03068v1)|null|\n"}, "Visual Localization": {"2201.13065": "|**2022-01-31**|**Rigidity Preserving Image Transformations and Equivariance in Perspective**|Lucas Brynte, Georg B\u00f6kman, Axel Flinth, Fredrik Kahl|[2201.13065v1](http://arxiv.org/abs/2201.13065v1)|null|\n", "2201.05386": "|**2022-01-14**|**SRVIO: Super Robust Visual Inertial Odometry for dynamic environments and challenging Loop-closure conditions**|Ali Samadzadeh, Ahmad Nickabadi|[2201.05386v1](http://arxiv.org/abs/2201.05386v1)|**[link](https://github.com/aa-samad/srvio)**|\n", "2112.09081": "|**2021-12-16**|**CrossLoc: Scalable Aerial Localization Assisted by Multimodal Synthetic Data**|Qi Yan, Jianhao Zheng, Simon Reding, Shanci Li, Iordan Doytchinov|[2112.09081v1](http://arxiv.org/abs/2112.09081v1)|**[link](https://github.com/topo-epfl/crossloc)**|\n", "2111.13063": "|**2021-11-25**|**MegLoc: A Robust and Accurate Visual Localization Pipeline**|Shuxue Peng, Zihang He, Haotian Zhang, Ran Yan, Chuting Wang, Qingtian Zhu, Xiao Liu|[2111.13063v1](http://arxiv.org/abs/2111.13063v1)|null|\n", "2110.04162": "|**2021-10-08**|**Semantic Image Alignment for Vehicle Localization**|Markus Herb, Matthias Lemberger, Marcel M. Schmitt, Alexander Kurz, Tobias Weiherer, Nassir Navab, Federico Tombari|[2110.04162v1](http://arxiv.org/abs/2110.04162v1)|null|\n", "2110.01967": "|**2021-10-05**|**Season-invariant GNSS-denied visual localization for UAVs**|Jouko Kinnari, Francesco Verdoja, Ville Kyrki|[2110.01967v1](http://arxiv.org/abs/2110.01967v1)|**[link](https://github.com/aalto-intelligent-robotics/sivl)**|\n", "2109.14916": "|**2021-09-30**|**Forming a sparse representation for visual place recognition using a neurorobotic approach**|Sylvain Colomer, Nicolas Cuperlier, Guillaume Bresson, Olivier Romain|[2109.14916v1](http://arxiv.org/abs/2109.14916v1)|null|\n", "2109.10571": "|**2021-09-22**|**Audio-Visual Grounding Referring Expression for Robotic Manipulation**|Yefei Wang, Kaili Wang, Yi Wang, Di Guo, Huaping Liu, Fuchun Sun|[2109.10571v1](http://arxiv.org/abs/2109.10571v1)|null|\n", "2109.04753": "|**2021-09-10**|**Line as a Visual Sentence: Context-aware Line Descriptor for Visual Localization**|Sungho Yoon, Ayoung Kim|[2109.04753v1](http://arxiv.org/abs/2109.04753v1)|**[link](https://github.com/yosungho/LineTR)**|\n", "2109.04527": "|**2021-09-09**|**CrowdDriven: A New Challenging Dataset for Outdoor Visual Localization**|Ara Jafarzadeh, Manuel Lopez Antequera, Pau Gargallo, Yubin Kuang, Carl Toft, Fredrik Kahl, Torsten Sattler|[2109.04527v1](http://arxiv.org/abs/2109.04527v1)|null|\n"}, "Keypoint Detection": {"2202.00448": "|**2022-02-01**|**Sim2Real Object-Centric Keypoint Detection and Description**|Chengliang Zhong, Chao Yang, Jinshan Qi, Fuchun Sun, Huaping Liu, Xiaodong Mu, Wenbing Huang|[2202.00448v1](http://arxiv.org/abs/2202.00448v1)|null|\n", "2201.03170": "|**2022-01-10**|**TFS Recognition: Investigating MPH]{Thai Finger Spelling Recognition: Investigating MediaPipe Hands Potentials**|Jinnavat Sanalohit, Tatpong Katanyukul|[2201.03170v1](http://arxiv.org/abs/2201.03170v1)|null|\n", "2201.02242": "|**2022-01-06**|**A Keypoint Detection and Description Network Based on the Vessel Structure for Multi-Modal Retinal Image Registration**|Aline Sindel, Bettina Hohberger, Sebastian Fassihi Dehcordi, Christian Mardin, Robert L\u00e4mmer, Andreas Maier, Vincent Christlein|[2201.02242v1](http://arxiv.org/abs/2201.02242v1)|null|\n", "2112.12193": "|**2021-12-22**|**Improved 2D Keypoint Detection in Out-of-Balance and Fall Situations -- combining input rotations and a kinematic model**|Michael Zw\u00f6lfer, Dieter Heinrich, Kurt Schindelwig, Bastian Wandt, Helge Rhodin, Joerg Spoerri, Werner Nachbauer|[2112.12193v1](http://arxiv.org/abs/2112.12193v1)|null|\n", "2112.12002": "|**2021-12-22**|**Looking Beyond Corners: Contrastive Learning of Visual Representations for Keypoint Detection and Description Extraction**|Henrique Siqueira, Patrick Ruhkamp, Ibrahim Halfaoui, Markus Karmann, Onay Urfalioglu|[2112.12002v1](http://arxiv.org/abs/2112.12002v1)|null|\n", "2112.10275": "|**2021-12-19**|**Parallel Multi-Scale Networks with Deep Supervision for Hand Keypoint Detection**|Renjie Li, Son Tran, Saurabh Garg, Katherine Lawler, Jane Alty, Quan Bai|[2112.10275v1](http://arxiv.org/abs/2112.10275v1)|null|\n", "2112.10258": "|**2021-12-19**|**GPU optimization of the 3D Scale-invariant Feature Transform Algorithm and a Novel BRIEF-inspired 3D Fast Descriptor**|Jean-Baptiste Carluer, Laurent Chauvin, Jie Luo, William M. Wells III, Ines Machado, Rola Harmouche, Matthew Toews|[2112.10258v1](http://arxiv.org/abs/2112.10258v1)|**[link](https://github.com/carluerjb/3d_sift_cuda)**|\n", "2112.06183": "|**2021-12-12**|**Few-shot Keypoint Detection with Uncertainty Learning for Unseen Species**|Changsheng Lu, Piotr Koniusz|[2112.06183v1](http://arxiv.org/abs/2112.06183v1)|null|\n", "2112.04910": "|**2021-12-09**|**Few-Shot Keypoint Detection as Task Adaptation via Latent Embeddings**|Mel Vecerik, Jackie Kay, Raia Hadsell, Lourdes Agapito, Jon Scholz|[2112.04910v2](http://arxiv.org/abs/2112.04910v2)|null|\n", "2112.02906": "|**2021-12-06**|**ALIKE: Accurate and Lightweight Keypoint Detection and Descriptor Extraction**|Xiaoming Zhao, Xingming Wu, Jinyu Miao, Weihai Chen, Peter C. Y. Chen, Zhengguo Li|[2112.02906v1](http://arxiv.org/abs/2112.02906v1)|**[link](https://github.com/Shiaoming/ALIKE)**|\n"}, "Image Matching": {"2202.00448": "|**2022-02-01**|**Sim2Real Object-Centric Keypoint Detection and Description**|Chengliang Zhong, Chao Yang, Jinshan Qi, Fuchun Sun, Huaping Liu, Xiaodong Mu, Wenbing Huang|[2202.00448v1](http://arxiv.org/abs/2202.00448v1)|null|\n", "2201.11296": "|**2022-01-27**|**Efficient divide-and-conquer registration of UAV and ground LiDAR point clouds through canopy shape context**|Jie Shao, Wei Yao, Peng Wan, Lei Luo, Jiaxin Lyu, Wuming Zhang|[2201.11296v1](http://arxiv.org/abs/2201.11296v1)|null|\n", "2112.12917": "|**2021-12-24**|**Multi-initialization Optimization Network for Accurate 3D Human Pose and Shape Estimation**|Zhiwei Liu, Xiangyu Zhu, Lu Yang, Xiang Yan, Ming Tang, Zhen Lei, Guibo Zhu, Xuetao Feng, Yan Wang, Jinqiao Wang|[2112.12917v1](http://arxiv.org/abs/2112.12917v1)|null|\n", "2112.10485": "|**2021-12-20**|**Scale-Net: Learning to Reduce Scale Differences for Large-Scale Invariant Image Matching**|Yujie Fu, Yihong Wu|[2112.10485v1](http://arxiv.org/abs/2112.10485v1)|null|\n", "2112.10258": "|**2021-12-19**|**GPU optimization of the 3D Scale-invariant Feature Transform Algorithm and a Novel BRIEF-inspired 3D Fast Descriptor**|Jean-Baptiste Carluer, Laurent Chauvin, Jie Luo, William M. Wells III, Ines Machado, Rola Harmouche, Matthew Toews|[2112.10258v1](http://arxiv.org/abs/2112.10258v1)|**[link](https://github.com/carluerjb/3d_sift_cuda)**|\n", "2112.05744": "|**2021-12-10**|**More Control for Free! Image Synthesis with Semantic Diffusion Guidance**|Xihui Liu, Dong Huk Park, Samaneh Azadi, Gong Zhang, Arman Chopikyan, Yuxiao Hu, Humphrey Shi, Anna Rohrbach, Trevor Darrell|[2112.05744v2](http://arxiv.org/abs/2112.05744v2)|null|\n", "2112.05240": "|**2021-12-08**|**Label-free virtual HER2 immunohistochemical staining of breast tissue using deep learning**|Bijie Bai, Hongda Wang, Yuzhu Li, Kevin de Haan, Francesco Colonnese, Yujie Wan, Jingyi Zuo, Ngan B. Doan, Xiaoran Zhang, Yijie Zhang, Jingxi Li, Wenjie Dong, Morgan Angus Darrow, Elham Kamangar, Han Sung Lee, Yair Rivenson, Aydogan Ozcan|[2112.05240v1](http://arxiv.org/abs/2112.05240v1)|null|\n", "2112.00821": "|**2021-12-01**|**FaSS-MVS -- Fast Multi-View Stereo with Surface-Aware Semi-Global Matching from UAV-borne Monocular Imagery**|Boitumelo Ruf, Martin Weinmann, Stefan Hinz|[2112.00821v1](http://arxiv.org/abs/2112.00821v1)|null|\n", "2112.00374": "|**2021-12-01**|**CLIPstyler: Image Style Transfer with a Single Text Condition**|Gihyun Kwon, Jong Chul Ye|[2112.00374v1](http://arxiv.org/abs/2112.00374v1)|**[link](https://github.com/paper11667/clipstyler)**|\n", "2111.14447": "|**2021-11-29**|**Zero-Shot Image-to-Text Generation for Visual-Semantic Arithmetic**|Yoad Tewel, Yoav Shalev, Idan Schwartz, Lior Wolf|[2111.14447v1](http://arxiv.org/abs/2111.14447v1)|**[link](https://github.com/yoadtew/zero-shot-image-to-text)**|\n"}, "SFM": {"2202.00015": "|**2022-01-31**|**Quenching Timescales in the IllustrisTNG Simulation**|Dan Walters, Joanna Woo, Sara L. Ellison|[2202.00015v1](http://arxiv.org/abs/2202.00015v1)|null|\n", "2201.08633": "|**2022-01-21**|**Multi-view Monocular Depth and Uncertainty Prediction with Deep SfM in Dynamic Environments**|Christian Homeyer, Oliver Lange, Christoph Schn\u00f6rr|[2201.08633v1](http://arxiv.org/abs/2201.08633v1)|null|\n", "2201.05230": "|**2022-01-13**|**NLP in Human Rights Research -- Extracting Knowledge Graphs About Police and Army Units and Their Commanders**|Daniel Bauer, Tom Longley, Yueen Ma, Tony Wilson|[2201.05230v1](http://arxiv.org/abs/2201.05230v1)|null|\n", "2201.04911": "|**2022-01-13**|**Strong [OIII]\u03bb5007 emission line compact galaxies in LAMOST DR9: Blueberries, Green Peas and Purple Grapes**|Siqi Liu, A-Li Luo, Huan Yang, Shi-Yin Shen, Jun-Xian Wang, Hao-Tong Zhang, Zhenya Zheng, Yi-Han Song, Xiao Kong, Jian-Ling Wang, Jian-Jun Chen|[2201.04911v1](http://arxiv.org/abs/2201.04911v1)|null|\n", "2201.03575": "|**2022-01-10**|**The variation of the gas content of galaxy groups and pairs compared to isolated galaxies**|Sambit Roychowdhury, Martin J. Meyer, Jonghwan Rhee, Martin A. Zwaan, Garima Chauhan, Luke J. M. Davies, Sabine Bellstedt, Simon P. Driver, Claudia del P. Lagos, Aaron S. G. Robotham, Joss Bland-Hawthorn, Richard Dodson, Benne W. Holwerda, Andrew M. Hopkins, Maritza A. Lara-Lopez, Angel R. Lopez-Sanchez, Danail Obreschkow, Kristof Rozgonyi, Matthew T. Whiting, Angus H. Wright|[2201.03575v1](http://arxiv.org/abs/2201.03575v1)|null|\n", "2201.03364": "|**2022-01-10**|**High-resolution Ecosystem Mapping in Repetitive Environments Using Dual Camera SLAM**|Brian M. Hopkinson, Suchendra M. Bhandarkar|[2201.03364v1](http://arxiv.org/abs/2201.03364v1)|**[link](https://github.com/bmhopkinson/hyslam)**|\n", "2112.14651": "|**2021-12-29**|**On the Instability of Relative Pose Estimation and RANSAC's Role**|Hongyi Fan, Joe Kileel, Benjamin Kimia|[2112.14651v1](http://arxiv.org/abs/2112.14651v1)|null|\n", "2112.08635": "|**2021-12-16**|**Road-aware Monocular Structure from Motion and Homography Estimation**|Wei Sui, Teng Chen, Jiaxin Zhang, Jiao Lu, Qian Zhang|[2112.08635v1](http://arxiv.org/abs/2112.08635v1)|null|\n", "2112.08171": "|**2021-12-13**|**Text Gestalt: Stroke-Aware Scene Text Image Super-Resolution**|Jingye Chen, Haiyang Yu, Jianqi Ma, Bin Li, Xiangyang Xue|[2112.08171v1](http://arxiv.org/abs/2112.08171v1)|null|\n", "2112.03288": "|**2021-12-06**|**Dense Depth Priors for Neural Radiance Fields from Sparse Input Views**|Barbara Roessle, Jonathan T. Barron, Ben Mildenhall, Pratul P. Srinivasan, Matthias Nie\u00dfner|[2112.03288v1](http://arxiv.org/abs/2112.03288v1)|null|\n"}, "Structure from Motion": {"2201.08131": "|**2022-01-20**|**GeoFill: Reference-Based Image Inpainting of Scenes with Complex Geometry**|Yunhan Zhao, Connelly Barnes, Yuqian Zhou, Eli Shechtman, Sohrab Amirghodsi, Charless Fowlkes|[2201.08131v1](http://arxiv.org/abs/2201.08131v1)|null|\n", "2201.04797": "|**2022-01-13**|**Scalable Cluster-Consistency Statistics for Robust Multi-Object Matching**|Yunpeng Shi, Shaohan Li, Tyler Maunu, Gilad Lerman|[2201.04797v1](http://arxiv.org/abs/2201.04797v1)|**[link](https://github.com/yunpeng-shi/fcc)**|\n", "2201.03364": "|**2022-01-10**|**High-resolution Ecosystem Mapping in Repetitive Environments Using Dual Camera SLAM**|Brian M. Hopkinson, Suchendra M. Bhandarkar|[2201.03364v1](http://arxiv.org/abs/2201.03364v1)|**[link](https://github.com/bmhopkinson/hyslam)**|\n", "2201.02279": "|**2022-01-06**|**De-rendering 3D Objects in the Wild**|Felix Wimbauer, Shangzhe Wu, Christian Rupprecht|[2201.02279v1](http://arxiv.org/abs/2201.02279v1)|null|\n", "2112.14651": "|**2021-12-29**|**On the Instability of Relative Pose Estimation and RANSAC's Role**|Hongyi Fan, Joe Kileel, Benjamin Kimia|[2112.14651v1](http://arxiv.org/abs/2112.14651v1)|null|\n", "2112.08635": "|**2021-12-16**|**Road-aware Monocular Structure from Motion and Homography Estimation**|Wei Sui, Teng Chen, Jiaxin Zhang, Jiao Lu, Qian Zhang|[2112.08635v1](http://arxiv.org/abs/2112.08635v1)|null|\n", "2112.05478": "|**2021-12-10**|**Critical configurations for three projective views**|Martin Br\u00e5telund|[2112.05478v1](http://arxiv.org/abs/2112.05478v1)|null|\n", "2112.05074": "|**2021-12-09**|**Critical configurations for two projective views, a new approach**|Martin Br\u00e5telund|[2112.05074v1](http://arxiv.org/abs/2112.05074v1)|null|\n", "2112.03288": "|**2021-12-06**|**Dense Depth Priors for Neural Radiance Fields from Sparse Input Views**|Barbara Roessle, Jonathan T. Barron, Ben Mildenhall, Pratul P. Srinivasan, Matthias Nie\u00dfner|[2112.03288v1](http://arxiv.org/abs/2112.03288v1)|null|\n", "2112.01349": "|**2021-12-02**|**MegBA: A High-Performance and Distributed Library for Large-Scale Bundle Adjustment**|Jie Ren, Wenteng Liang, Ran Yan, Luo Mai, Shiwen Liu, Xiao Liu|[2112.01349v2](http://arxiv.org/abs/2112.01349v2)|**[link](https://github.com/megviirobot/megba)**|\n"}, "3D Reconstruction": {"2201.12533": "|**2022-01-29**|**Light field Rectification based on relative pose estimation**|Xiao Huo, Dongyang Jin, Saiping Zhang, Fuzheng Yang|[2201.12533v1](http://arxiv.org/abs/2201.12533v1)|null|\n", "2201.12184": "|**2022-01-28**|**A tomographic workflow to enable deep learning for X-ray based foreign object detection**|Math\u00e9 T. Zeegers, Tristan van Leeuwen, Dani\u00ebl M. Pelt, Sophia Bethany Coban, Robert van Liere, Kees Joost Batenburg|[2201.12184v1](http://arxiv.org/abs/2201.12184v1)|null|\n", "2201.12170": "|**2022-01-28**|**Unsupervised Single-shot Depth Estimation using Perceptual Reconstruction**|Christoph Angermann, Matthias Schwab, Markus Haltmeier, Christian Laubichler, Steinbj\u00f6rn J\u00f3nsson|[2201.12170v2](http://arxiv.org/abs/2201.12170v2)|**[link](https://github.com/anger-man/unsupervised-depth-estimation)**|\n", "2201.11579": "|**2022-01-27**|**Total variation-based phase retrieval for diffraction tomography**|Robert Beinert, Michael Quellmalz|[2201.11579v1](http://arxiv.org/abs/2201.11579v1)|**[link](https://github.com/michaelquellmalz/fourierodt)**|\n", "2201.10865": "|**2022-01-26**|**On the Issues of TrueDepth Sensor Data for Computer Vision Tasks Across Different iPad Generations**|Steffen Urban, Thomas Lindemeier, David Dobbelstein, Matthias Haenel|[2201.10865v1](http://arxiv.org/abs/2201.10865v1)|null|\n", "2201.09463": "|**2022-01-24**|**Cyber Mobility Mirror for Enabling Cooperative Driving Automation: A Co-Simulation Platform**|Zhengwei Bai, Guoyuan Wu, Xuewei Qi, Kentaro Oguchi, Matthew J. Barth|[2201.09463v1](http://arxiv.org/abs/2201.09463v1)|null|\n", "2201.09373": "|**2022-01-23**|**Unsupervised Severely Deformed Mesh Reconstruction (DMR) from a Single-View Image**|Jie Mei, Jingxi Yu, Suzanne Romain, Craig Rose, Kelsey Magrane, Graeme LeeSon, Jenq-Neng Hwang|[2201.09373v1](http://arxiv.org/abs/2201.09373v1)|null|\n", "2201.09318": "|**2022-01-23**|**Sparse-view Cone Beam CT Reconstruction using Data-consistent Supervised and Adversarial Learning from Scarce Training Data**|Anish Lahiri, Marc Klasky, Jeffrey A. Fessler, Saiprasad Ravishankar|[2201.09318v1](http://arxiv.org/abs/2201.09318v1)|null|\n", "2201.09048": "|**2022-01-22**|**Phase-SLAM: Phase Based Simultaneous Localization and Mapping for Mobile Structured Light Illumination Systems**|Xi Zheng, Rui Ma, Rui Gao, Qi Hao|[2201.09048v1](http://arxiv.org/abs/2201.09048v1)|**[link](https://github.com/zhengxi-git/phase-slam)**|\n", "2201.08845": "|**2022-01-21**|**Point-NeRF: Point-based Neural Radiance Fields**|Qiangeng Xu, Zexiang Xu, Julien Philip, Sai Bi, Zhixin Shu, Kalyan Sunkavalli, Ulrich Neumann|[2201.08845v1](http://arxiv.org/abs/2201.08845v1)|null|\n"}, "Depth Estimation": {"2201.12533": "|**2022-01-29**|**Light field Rectification based on relative pose estimation**|Xiao Huo, Dongyang Jin, Saiping Zhang, Fuzheng Yang|[2201.12533v1](http://arxiv.org/abs/2201.12533v1)|null|\n", "2201.12437": "|**2022-01-28**|**Task-Focused Few-Shot Object Detection for Robot Manipulation**|Brent Griffin|[2201.12437v1](http://arxiv.org/abs/2201.12437v1)|**[link](https://github.com/griffbr/tfod)**|\n", "2201.12170": "|**2022-01-28**|**Unsupervised Single-shot Depth Estimation using Perceptual Reconstruction**|Christoph Angermann, Matthias Schwab, Markus Haltmeier, Christian Laubichler, Steinbj\u00f6rn J\u00f3nsson|[2201.12170v2](http://arxiv.org/abs/2201.12170v2)|**[link](https://github.com/anger-man/unsupervised-depth-estimation)**|\n", "2201.11924": "|**2022-01-28**|**Close the Visual Domain Gap by Physics-Grounded Active Stereovision Depth Sensor Simulation**|Xiaoshuai Zhang, Rui Chen, Fanbo Xiang, Yuzhe Qin, Jiayuan Gu, Zhan Ling, Minghua Liu, Peiyu Zeng, Songfang Han, Zhiao Huang, Tongzhou Mu, Jing Xu, Hao Su|[2201.11924v1](http://arxiv.org/abs/2201.11924v1)|null|\n", "2201.10848": "|**2022-01-26**|**Comparison of Depth Estimation Setups from Stereo Endoscopy and Optical Tracking for Point Measurements**|Lukas Burger, Lalith Sharan, Samantha Fischer, Julian Brand, Maximillian Hehl, Gabriele Romano, Matthias Karck, Raffaele De Simone, Ivo Wolf, Sandy Engelhardt|[2201.10848v1](http://arxiv.org/abs/2201.10848v1)|null|\n", "2201.08131": "|**2022-01-20**|**GeoFill: Reference-Based Image Inpainting of Scenes with Complex Geometry**|Yunhan Zhao, Connelly Barnes, Yuqian Zhou, Eli Shechtman, Sohrab Amirghodsi, Charless Fowlkes|[2201.08131v1](http://arxiv.org/abs/2201.08131v1)|null|\n", "2201.07609": "|**2022-01-19**|**A Confidence-based Iterative Solver of Depths and Surface Normals for Deep Multi-view Stereo**|Wang Zhao, Shaohui Liu, Yi Wei, Hengkai Guo, Yong-Jin Liu|[2201.07609v1](http://arxiv.org/abs/2201.07609v1)|**[link](https://github.com/thuzhaowang/idn-solver)**|\n", "2201.07436": "|**2022-01-19**|**Global-Local Path Networks for Monocular Depth Estimation with Vertical CutDepth**|Doyeon Kim, Woonghyun Ga, Pyungwhan Ahn, Donggyu Joo, Sehwan Chun, Junmo Kim|[2201.07436v2](http://arxiv.org/abs/2201.07436v2)|**[link](https://github.com/vinvino02/GLPDepth)**|\n", "2201.05761": "|**2022-01-15**|**A Survey on RGB-D Datasets**|Alexandre Lopes, Roberto Souza, Helio Pedrini|[2201.05761v1](http://arxiv.org/abs/2201.05761v1)|**[link](https://github.com/alelopes/RGBD-Datasets)**|\n", "2201.04485": "|**2022-01-12**|**Depth Estimation from Single-shot Monocular Endoscope Image Using Image Domain Adaptation And Edge-Aware Depth Estimation**|Masahiro Oda, Hayato Itoh, Kiyohito Tanaka, Hirotsugu Takabatake, Masaki Mori, Hiroshi Natori, Kensaku Mori|[2201.04485v1](http://arxiv.org/abs/2201.04485v1)|null|\n"}, "Long Term Localization": {"2110.00128": "|**2021-09-30**|**Probabilistic Object Maps for Long-Term Robot Localization**|Amanda Adkins, Joydeep Biswas|[2110.00128v2](http://arxiv.org/abs/2110.00128v2)|**[link](https://github.com/ut-amrl/pom_localization)**|\n", "2103.14826": "|**2021-03-27**|**Compact 3D Map-Based Monocular Localization Using Semantic Edge Alignment**|Kejie Qiu, Shenzhou Chen, Jiahui Zhang, Rui Huang, Le Cui, Siyu Zhu, Ping Tan|[2103.14826v1](http://arxiv.org/abs/2103.14826v1)|null|\n", "2103.13224": "|**2021-03-24**|**Pole-like Objects Mapping and Long-Term Robot Localization in Dynamic Urban Scenarios**|Zhihao Wang, Silin Li, Ming Cao, Haoyao Chen, Yunhui Liu|[2103.13224v3](http://arxiv.org/abs/2103.13224v3)|**[link](https://github.com/HITSZ-NRSL/long-term-localization)**|\n", "2009.07061": "|**2020-09-15**|**RaLL: End-to-end Radar Localization on Lidar Map Using Differentiable Measurement Model**|Huan Yin, Runjian Chen, Yue Wang, Rong Xiong|[2009.07061v3](http://arxiv.org/abs/2009.07061v3)|**[link](https://github.com/ZJUYH/RaLL)**|\n", "2005.04644": "|**2020-05-10**|**Radar-on-Lidar: metric radar localization on prior lidar maps**|Huan Yin, Yue Wang, Li Tang, Rong Xiong|[2005.04644v3](http://arxiv.org/abs/2005.04644v3)|null|\n", "2002.09267": "|**2020-02-21**|**A copula-based time series model for global horizontal irradiation**|Alfred M\u00fcller, Matthias Reuber|[2002.09267v1](http://arxiv.org/abs/2002.09267v1)|null|\n", "1911.00663": "|**2019-11-02**|**Furniture Free Mapping using 3D Lidars**|Zhenpeng He, Jiawei Hou, S\u00f6ren Schwertfeger|[1911.00663v2](http://arxiv.org/abs/1911.00663v2)|null|\n", "1910.12728": "|**2019-10-28**|**Real-Time, Environmentally-Robust 3D LiDAR Localization**|Yilong Zhu, Bohuan Xue, Linwei Zheng, Huaiyang Huang, Ming Liu, Rui Fan|[1910.12728v1](http://arxiv.org/abs/1910.12728v1)|null|\n", "1910.10550": "|**2019-10-23**|**Long-Term Urban Vehicle Localization Using Pole Landmarks Extracted from 3-D Lidar Scans**|Alexander Schaefer, Daniel B\u00fcscher, Johan Vertens, Lukas Luft, Wolfram Burgard|[1910.10550v1](http://arxiv.org/abs/1910.10550v1)|**[link](https://github.com/acschaefer/polex)**|\n", "1908.06387": "|**2019-08-18**|**Fine-Grained Segmentation Networks: Self-Supervised Segmentation for Improved Long-Term Visual Localization**|M\u00e5ns Larsson, Erik Stenborg, Carl Toft, Lars Hammarstrand, Torsten Sattler, Fredrik Kahl|[1908.06387v1](http://arxiv.org/abs/1908.06387v1)|**[link](https://github.com/maunzzz/fine-grained-segmentation-networks)**|\n"}, "Object Track": {"2201.13178": "|**2022-01-31**|**Few-Shot Backdoor Attacks on Visual Object Tracking**|Yiming Li, Haoxiang Zhong, Xingjun Ma, Yong Jiang, Shu-Tao Xia|[2201.13178v1](http://arxiv.org/abs/2201.13178v1)|**[link](https://github.com/hxzhong1997/fsba)**|\n", "2201.13066": "|**2022-01-31**|**Single Object Tracking: A Survey of Methods, Datasets, and Evaluation Metrics**|Zahra Soleimanitaleb, Mohammad Ali Keyvanrad|[2201.13066v1](http://arxiv.org/abs/2201.13066v1)|null|\n", "2201.10602": "|**2022-01-25**|**Jacobian Computation for Cumulative B-splines on SE(3) and Application to Continuous-Time Object Tracking**|Javier Tirado, Javier Civera|[2201.10602v1](http://arxiv.org/abs/2201.10602v1)|null|\n", "2201.09296": "|**2022-01-23**|**A Survey for Deep RGBT Tracking**|Zhangyong Tang, Tianyang Xu, Xiao-Jun Wu|[2201.09296v2](http://arxiv.org/abs/2201.09296v2)|null|\n", "2201.09207": "|**2022-01-23**|**Visual Object Tracking on Multi-modal RGB-D Videos: A Review**|Xue-Feng Zhu, Tianyang Xu, Xiao-Jun Wu|[2201.09207v2](http://arxiv.org/abs/2201.09207v2)|null|\n", "2201.08949": "|**2022-01-22**|**Temporal Aggregation for Adaptive RGBT Tracking**|Zhangyong Tang, Tianyang Xu, Xiao-Jun Wu|[2201.08949v2](http://arxiv.org/abs/2201.08949v2)|**[link](https://github.com/zhangyong-tang/taat)**|\n", "2201.08673": "|**2022-01-21**|**Exploring Fusion Strategies for Accurate RGBT Visual Object Tracking**|Zhangyong Tang, Tianyang Xu, Hui Li, Xiao-Jun Wu, Xuefeng Zhu, Josef Kittler|[2201.08673v1](http://arxiv.org/abs/2201.08673v1)|null|\n", "2201.08379": "|**2022-01-20**|**Learning Pixel Trajectories with Multiscale Contrastive Random Walks**|Zhangxing Bian, Allan Jabri, Alexei A. Efros, Andrew Owens|[2201.08379v1](http://arxiv.org/abs/2201.08379v1)|null|\n", "2201.07665": "|**2022-01-19**|**Semi-automatic 3D Object Keypoint Annotation and Detection for the Masses**|Kenneth Blomqvist, Jen Jen Chung, Lionel Ott, Roland Siegwart|[2201.07665v1](http://arxiv.org/abs/2201.07665v1)|**[link](https://github.com/ethz-asl/object_keypoints)**|\n", "2201.07619": "|**2022-01-19**|**CAST: Character labeling in Animation using Self-supervision by Tracking**|Oron Nir, Gal Rapoport, Ariel Shamir|[2201.07619v1](http://arxiv.org/abs/2201.07619v1)|**[link](https://github.com/oronnir/cast)**|\n"}, "Dynamic Obstacle Avoid": {"2112.12465": "|**2021-12-23**|**Missing Velocity in Dynamic Obstacle Avoidance based on Deep Reinforcement Learning**|Fabian Hart, Martin Waltz, Ostap Okhrin|[2112.12465v2](http://arxiv.org/abs/2112.12465v2)|null|\n", "2109.11636": "|**2021-09-23**|**All-in-One: A DRL-based Control Switch Combining State-of-the-art Navigation Planners**|Linh K\u00e4stner, Johannes Cox, Teham Buiyan, Jens Lambrecht|[2109.11636v1](http://arxiv.org/abs/2109.11636v1)|**[link](https://github.com/ignc-research/all-in-one-DRL-planner)**|\n", "2106.04315": "|**2021-06-08**|**Learning Riemannian Manifolds for Geodesic Motion Skills**|Hadi Beik-Mohammadi, S\u00f8ren Hauberg, Georgios Arvanitidis, Gerhard Neumann, Leonel Rozo|[2106.04315v2](http://arxiv.org/abs/2106.04315v2)|null|\n", "2104.11655": "|**2021-04-23**|**Speed Planning Using Bezier Polynomials with Trapezoidal Corridors**|Jialun Li, Xiaojia Xie, Hengbo Ma, Xiao Liu, Jianping He|[2104.11655v1](http://arxiv.org/abs/2104.11655v1)|null|\n", "2104.03663": "|**2021-04-08**|**Connecting Deep-Reinforcement-Learning-based Obstacle Avoidance with Conventional Global Planners using Waypoint Generators**|Linh K\u00e4stner, Teham Buiyan, Xinlin Zhao, Zhengcheng Shen, Cornelius Marx, Jens Lambrecht|[2104.03663v1](http://arxiv.org/abs/2104.03663v1)|**[link](https://github.com/ignc-research/arena-rosnav)**|\n", "2102.13283": "|**2021-02-26**|**Multi-Agent Path Planning based on MPC and DDPG**|Junxiao Xue, Xiangyan Kong, Bowei Dong, Mingliang Xu|[2102.13283v1](http://arxiv.org/abs/2102.13283v1)|null|\n", "2008.00792": "|**2020-08-03**|**Nonlinear MPC for Collision Avoidance and Controlof UAVs With Dynamic Obstacles**|Bj\u00f6rn Lindqvist, Sina Sharif Mansouri, Ali-akbar Agha-mohammadi, George Nikolakopoulos|[2008.00792v1](http://arxiv.org/abs/2008.00792v1)|null|\n", "2007.10743": "|**2020-07-21**|**Leveraging Stereo-Camera Data for Real-Time Dynamic Obstacle Detection and Tracking**|Thomas Eppenberger, Gianluca Cesari, Marcin Dymczyk, Roland Siegwart, Renaud Dub\u00e9|[2007.10743v1](http://arxiv.org/abs/2007.10743v1)|null|\n", "2002.04349": "|**2020-02-11**|**Robot Navigation with Map-Based Deep Reinforcement Learning**|Guangda Chen, Lifan Pan, Yu'an Chen, Pei Xu, Zhiqiang Wang, Peichen Wu, Jianmin Ji, Xiaoping Chen|[2002.04349v1](http://arxiv.org/abs/2002.04349v1)|null|\n", "1906.02919": "|**2019-06-07**|**EVDodgeNet: Deep Dynamic Obstacle Dodging with Event Cameras**|Nitin J. Sanket, Chethan M. Parameshwara, Chahat Deep Singh, Ashwin V. Kuruttukulam, Cornelia Ferm\u00fcller, Davide Scaramuzza, Yiannis Aloimonos|[1906.02919v3](http://arxiv.org/abs/1906.02919v3)|**[link](https://github.com/prgumd/EVDodgeNet)**|\n"}, "PointCloud": {"2112.08626": "|**2021-12-16**|**Analysis and Evaluation of Kinect-based Action Recognition Algorithms**|Lei Wang|[2112.08626v1](http://arxiv.org/abs/2112.08626v1)|**[link](https://github.com/LeiWangR/HDG)**|\n", "2109.07288": "|**2021-09-15**|**Two algorithms for vehicular obstacle detection in sparse pointcloud**|Simone Mentasti, Matteo Matteucci, Stefano Arrigoni, Federico Cheli|[2109.07288v1](http://arxiv.org/abs/2109.07288v1)|null|\n", "2109.06250": "|**2021-09-13**|**TTM: Terrain Traversability Mapping for Autonomous Excavators**|Tianrui Guan, Zhenpeng He, Dinesh Manocha, Liangjun Zhang|[2109.06250v2](http://arxiv.org/abs/2109.06250v2)|null|\n", "2108.13105": "|**2021-08-30**|**COMPRA: A COMPact Reactive Autonomy framework for subterranean MAV based search-and-rescue operations**|Bj\u00f6rn Lindqvist, Christoforos Kanellakis, Sina Sharif Mansouri, Ali-akbar Agha-mohammadi, George Nikolakopoulos|[2108.13105v1](http://arxiv.org/abs/2108.13105v1)|null|\n", "2108.06417": "|**2021-08-13**|**Is Pseudo-Lidar needed for Monocular 3D Object detection?**|Dennis Park, Rares Ambrus, Vitor Guizilini, Jie Li, Adrien Gaidon|[2108.06417v1](http://arxiv.org/abs/2108.06417v1)|**[link](https://github.com/tri-ml/dd3d)**|\n", "2108.05630": "|**2021-08-12**|**3D-SiamRPN: An End-to-End Learning Method for Real-Time 3D Single Object Tracking Using Raw Point Cloud**|Zheng Fang, Sifan Zhou, Yubo Cui, Sebastian Scherer|[2108.05630v1](http://arxiv.org/abs/2108.05630v1)|null|\n", "2108.02976": "|**2021-08-06**|**On Bundle Adjustment for Multiview PointCloud Registration**|Huaiyang Huang, Yuxiang Sun, Jin Wu, Jiaohao Jiao, Xiangcheng Hu, Linwei Zheng, Lujia Wang, Ming Liu|[2108.02976v1](http://arxiv.org/abs/2108.02976v1)|null|\n", "2106.16129": "|**2021-06-30**|**Recurrently Estimating Reflective Symmetry Planes from Partial Pointclouds**|Mihaela C\u0103t\u0103lina Stoian, Tommaso Cavallari|[2106.16129v1](http://arxiv.org/abs/2106.16129v1)|null|\n", "2106.15366": "|**2021-06-26**|**TANet++: Triple Attention Network with Filtered Pointcloud on 3D Detection**|Cong Ma|[2106.15366v2](http://arxiv.org/abs/2106.15366v2)|null|\n", "2105.02961": "|**2021-04-28**|**UVStyle-Net: Unsupervised Few-shot Learning of 3D Style Similarity Measure for B-Reps**|Peter Meltzer, Hooman Shayani, Amir Khasahmadi, Pradeep Kumar Jayaraman, Aditya Sanghi, Joseph Lambourne|[2105.02961v3](http://arxiv.org/abs/2105.02961v3)|**[link](https://github.com/AutodeskAILab/UVStyle-Net)**|\n"}}